{
  "component": "elvt-chip",
  "version": "0.0.28-alpha",
  "lastUpdated": "2025-08-12T12:23:28.324Z",
  "changelog": [
    {
      "version": "0.0.25-alpha",
      "date": "2025-06-15",
      "type": "minor",
      "changes": [
        {
          "type": "feature",
          "title": "Adjust/Revisit Chip Component Styles",
          "description": "Added adjust/revisit chip component styles",
          "commit": "ab68982",
          "impact": "visual",
          "breakingChange": false,
          "author": "pberckey",
          "url": "https://github.com/inform-elevate/elevate-core-ui/commit/ab68982339f078783aeab8a01af5ac1e1736e06a"
        }
      ]
    },
    {
      "version": "0.0.24-alpha",
      "date": "2025-05-15",
      "type": "minor",
      "changes": [
        {
          "type": "feature",
          "title": "Add Elevate Chip",
          "description": "Added add elevate chip",
          "commit": "86a7027",
          "impact": "functionality",
          "breakingChange": false,
          "author": "pberckey",
          "url": "https://github.com/inform-elevate/elevate-core-ui/commit/86a7027d09d08ad1aea9deb89b7475fe7138dda2"
        }
      ]
    },
    {
      "version": "0.0.22-alpha",
      "date": "2025-03-25",
      "type": "minor",
      "changes": [
        {
          "type": "feature",
          "title": "Refac: Add Shape Enum for both chip and badge",
          "description": "Added refac: add shape enum for both chip and badge",
          "commit": "102fd05",
          "impact": "functionality",
          "breakingChange": false,
          "author": "paolainform",
          "url": "https://github.com/inform-elevate/elevate-core-ui/commit/102fd0586910f78411f3402b4610ab045f1c26f3"
        }
      ]
    },
    {
      "version": "0.0.21-alpha",
      "date": "2025-02-28",
      "type": "minor",
      "changes": [
        {
          "type": "feature",
          "title": "Add Chip Wrapper",
          "description": "Added add chip wrapper",
          "commit": "a99a0bf",
          "impact": "functionality",
          "breakingChange": false,
          "author": "paolainform",
          "url": "https://github.com/inform-elevate/elevate-core-ui/commit/a99a0bf65331fad9c24f4284e584c5c58e23e735"
        }
      ]
    }
  ],
  "deprecations": [],
  "upcomingChanges": [
    {
      "version": "0.1.0",
      "plannedDate": "2025-09-01",
      "description": "Stable release with finalized API",
      "changes": [
        "API stabilization",
        "Performance optimizations",
        "Enhanced accessibility features"
      ]
    }
  ],
  "metadata": {
    "totalVersions": 4,
    "firstVersion": "0.0.21-alpha",
    "storyCount": 0,
    "testCount": 0,
    "fileCount": 0,
    "lastCommit": "ab68982339f078783aeab8a01af5ac1e1736e06a",
    "source": "GitHub API",
    "apiUrl": "https://api.github.com/repos/inform-elevate/elevate-core-ui",
    "filteredCommits": "4/21"
  }
}